MANIFEST.in
README.md
setup.py
tox.ini
drf_jwt_util/__init__.py
drf_jwt_util/apps.py
drf_jwt_util/auth.py
drf_jwt_util/email.py
drf_jwt_util/jwt.py
drf_jwt_util/serializers.py
drf_jwt_util/settings.py
drf_jwt_util/signing.py
drf_jwt_util/views.py
drf_jwt_util.egg-info/PKG-INFO
drf_jwt_util.egg-info/SOURCES.txt
drf_jwt_util.egg-info/dependency_links.txt
drf_jwt_util.egg-info/requires.txt
drf_jwt_util.egg-info/top_level.txt
drf_jwt_util/locale/en/LC_MESSAGES/django.mo
drf_jwt_util/locale/en/LC_MESSAGES/django.po
drf_jwt_util/locale/ja/LC_MESSAGES/django.mo
drf_jwt_util/locale/ja/LC_MESSAGES/django.po
drf_jwt_util/social/__init__.py
drf_jwt_util/social/apps.py
drf_jwt_util/social/serializers.py
drf_jwt_util/social/tests.py
drf_jwt_util/social/views.py
drf_jwt_util/templates/drf_jwt_util/email/acitvation_message.txt
drf_jwt_util/templates/drf_jwt_util/email/acitvation_subject.txt
drf_jwt_util/templates/drf_jwt_util/email/confirmation_message.txt
drf_jwt_util/templates/drf_jwt_util/email/confirmation_subject.txt
drf_jwt_util/templates/drf_jwt_util/email/passwordreset_message.txt
drf_jwt_util/templates/drf_jwt_util/email/passwordreset_subject.txt