Metadata-Version: 1.0
Name: drf-jwt-util
Version: 0.1.8
Summary: drf jwt util
Home-page: https://github.com/shunsukeaihara/drf_jwt_util
Author: Shunsuke Aihara
Author-email: aihara@argmax.jp
License: MIT License
Platform: UNKNOWN
